intuitive_vectorscript/__init__.py
intuitive_vectorscript/dialog.py
intuitive_vectorscript/dialog_item.py
intuitive_vectorscript/item_multiple_choices.py
intuitive_vectorscript/item_single_value_field.py
intuitive_vectorscript/main.py
intuitive_vectorscript/test.py
intuitive_vectorscript/usefull_classes.py
intuitive_vectorscript/usefull_functions.py
intuitive_vectorscript-0.1.3.dist-info/LICENSE
intuitive_vectorscript-0.1.3.dist-info/METADATA
intuitive_vectorscript-0.1.3.dist-info/WHEEL
intuitive_vectorscript-0.1.3.dist-info/top_level.txt
intuitive_vectorscript-0.1.3.dist-info/RECORD
