Metadata-Version: 2.1
Name: intuitive-vectorscript
Version: 0.1.3
Summary: Some useful function and classes for Vectorworks python scripting
Home-page: UNKNOWN
Author: brvn (Lukas Tobler)
Author-email: 
License: UNKNOWN
